Workbook

Sheet разметка
A1: Benchmark
A2: review_id | B2: club | C2: rating | D2: date_iso | E2: text | F2: вход_фейсконтроль_охрана | H2: музыка_звук | I2: персонал_сервис | J2: бар_еда | K2: помещение_комфорт | L2: цены_финвопросы | M2: платный_вход | N2: безопасность_кражи | O2: прочее | P2: контингент
A3: Ci9DQUlRQUNvZENodHljRjlvT2xaS05scDJSbll4VEZNNFozUXRZVk5vWm1KM1QxRRAB | B3: Микс Afterparty | C3: 5 | D3: 2026-03-21T23:44:29Z | E3: роскошное заведение с мягкой и приятной музыкой. рекомендую к посещению! хостел заслуживают отдельного внимания! | F3: 0 | H3: 0 | I3: 0 | J3: 0 | K3: 0 | L3: 0 | M3: 0 | N3: 0 | O3: 0 | P3: 0
A4: ChdDSUhNMG9nS0VJQ0FnSURwN19Qa3NRRRAB | B4: KULTURA | C4: 1 | D4: 2023-09-01T00:08:43Z | E4: Максимально неприветливый персонал, охрана на каждую проблему агрессивно реагирует, берут за руки, правила сами выстанавливают, моему другу предложили депозит 5к без объяснения, хотя мы были компанией. В итоге выгнали за то, что стакан не там поставил, другого за опьянение в КЛУБЕ, другого за национальность!!!! | F4: 1 | H4: 0 | I4: 1 | J4: 0 | K4: 0 | L4: 0 | M4: 0 | N4: 0 | O4: 0 | P4: 0
A5: ChdDSUhNMG9nS0VJQ0FnSUNYNVliMHlRRRAB | B5: Live Stars | C5: 5 | D5: 2024-10-18T20:04:58Z | E5: Я люблю это заведение , тут самая ламповая атмосфера. Отличные мероприятия. Самый лучший бар) на самый притязательный вкус😊 | F5: 0 | H5: 0 | I5: 0 | J5: 0 | K5: 0 | L5: 0 | M5: 0 | N5: 0 | O5: 0 | P5: 0
A6: Ci9DQUlRQUNvZENodHljRjlvT2xWd1N6WkZXRlJIV1U5T056SjJSa1pVTVdkbFQwRRAB | B6: Молодёжь | C6: 5 | D6: 2026-06-02T20:57:57Z | E6: Хорошее место, рекомендую, хорошие сотрудники) | F6: 0 | H6: 0 | I6: 0 | J6: 0 | K6: 0 | L6: 0 | M6: 0 | N6: 0 | O6: 0 | P6: 0
A7: ChdDSUhNMG9nS0VJQ0FnSUR2NEszdW93RRAB | B7: KULTURA | C7: 5 | D7: 2024-12-16T17:18:53Z | E7: Доброго вечера.!Зашла в клуб с подругами ,и это просто улет.Напитки недорогие ,вкусная еда .Официанты такие милые,один даже сделал комплимент что круто выгляжу.Персонал супер дружелюбный ,обязательно ещё раз приду . | F7: 0 | H7: 0 | I7: 0 | J7: 0 | K7: 0 | L7: 0 | M7: 0 | N7: 0 | O7: 0 | P7: 0
A8: ChdDSUhNMG9nS0VJQ0FnSUROMTdQWTNnRRAB | B8: МТ music bar | C8: 1 | D8: 2024-01-27T01:57:17Z | E8: Ahlaksiz guvenlik gorevlisi içeri girmek için 5000 rusvet istedi | F8: 1 | H8: 0 | I8: 0 | J8: 0 | K8: 0 | L8: 0 | M8: 1 | N8: 0 | O8: 0 | P8: 0
A9: Ci9DQUlRQUNvZENodHljRjlvT21Wb1JuazFOWEpyUzFWSGVEZGZWMGhwTUVsUVoyYxAB | B9: LASKI ВИНО И ПЛЯСКИ | C9: 5 | D9: 2025-06-15T18:39:49Z | E9: Все классно) достаточно легко пройти, доброжелательная атмосфера, без пафоса как в соседних местах, можно вкусно поесть внутри, потанцевать, музыка движовая, а также есть комната где можно подышать) Кому не понравилось - вы просто рано пришли!)) | F9: 0 | H9: 0 | I9: 0 | J9: 0 | K9: 0 | L9: 0 | M9: 0 | N9: 0 | O9: 0 | P9: 0
A10: ChZDSUhNMG9nS0VJQ0FnSUNudmVINVp3EAE | B10: GIPSY | C10: 5 | D10: 2024-09-29T00:41:48Z | E10: В данный момент нахожусь в данном заведении. Это один из лучших клубов где я был. Ребят, спасибо Вам большое, за такую прекрасную ночь, Вы лучшие. Всем рекомендую посетить данное заведение❤️ | F10: 0 | H10: 0 | I10: 0 | J10: 0 | K10: 0 | L10: 0 | M10: 0 | N10: 0 | O10: 0 | P10: 0
A11: ChdDSUhNMG9nS0VJQ0FnSURtLUk2UWlRRRAB | B11: Мутабор | C11: 5 | D11: 2022-01-18T15:07:47Z | E11: Необычная локация, просторно | F11: 0 | H11: 0 | I11: 0 | J11: 0 | K11: 0 | L11: 0 | M11: 0 | N11: 0 | O11: 0 | P11: 0
A12: Ci9DQUlRQUNvZENodHljRjlvT2xWaU5IWTJYM05GZHpoWlMwMXpXSFJzU0ZCRldrRRAB | B12: Молодёжь | C12: 5 | D12: 2026-08-01T01:28:39Z | E12: Отличное заведение. Обязательно внрнемся. Персонал и охрана очень приветлиые | F12: 0 | H12: 0 | I12: 0 | J12: 0 | K12: 0 | L12: 0 | M12: 0 | N12: 0 | O12: 0 | P12: 0
A13: ChZDSUhNMG9nS0VJQ0FnSURtdF8tQkRnEAE | B13: RNDM | C13: 5 | D13: 2022-02-12T13:09:09Z | E13: Короче рандом, я у вас кучу раз был и в благородство играть не буду. Выполнишь пару условий - и мы в расчете. Хрен его знает на кой ляд вам эти дабстепы, джанглы, драмэндбейсы сдались, учитывая что вакантное место «русского трезора» сейчас свободно, дайте нам больше тееехна, ну поставьте там клеточку перед диджейкой, расставьте пару чб телевизоров, на определенных тусах можно камеры заклеивать, а то декорации на тусовках отличаются в основном только работой со светом, но я в чужие дела не лезу, это скорее вопрос к промо | F13: 0 | H13: 0 | I13: 0 | J13: 0 | K13: 1 | L13: 0 | M13: 0 | N13: 0 | O13: 0 | P13: 0
A14: ChdDSUhNMG9nS0VJQ0FnSUN4eFlTSjdnRRAB | B14: Пропаганда | C14: 1 | D14: 2023-05-21T22:25:05Z | E14: Охранник на входе не пропустил, причём абсолютно без причины. Был прилично одет и вежлив, русский язык для меня родной. Очень жаль, так как немного клубов с хорошей электронной музыкой в Мск. Очевидно сюда не вернусь, но рекомендую администрации обратить внимание на работу вышибал. Расизм и произвол в 21 веке, иначе не назвать. | F14: 1 | H14: 0 | I14: 0 | J14: 0 | K14: 0 | L14: 0 | M14: 0 | N14: 0 | O14: 0 | P14: 0
... A151: Ci9DQUlRQUNvZENodHljRjlvT2xaM1ZUVmllbWs1Y3pSaldHMU5NSFY0ZERWU01WRRAB | B151: Микс Afterparty | C151: 5 | D151: 2026-03-26T14:48:46Z | E151: Великолепный клуб,крутая атмосфера, шикарный дизайн и обстановка! Честный бар, хороший фейс контроль. Контингент всегда допускается адекватный и прекрасно выглядевший! Всегда | F151: 0 | H151: 0 | I151: 0 | J151: 0 | K151: 0 | L151: 0 | M151: 0 | N151: 0 | O151: 0 | P151: 0

Sheet частоты
A1: Частоты тем в размеченной выборке
A3: Всего отзывов | B3: =COUNTA(разметка!A3:A151) -> 149
A4: Из них негативных (оценка ≤3) | B4: =COUNTIF(разметка!C3:C151,"<=3") -> 54
A6: Тема | B6: Упоминаний всего | C6: Доля от всех | D6: Упоминаний в негативе | E6: Доля в негативе
A8: вход_фейсконтроль_охрана | B8: =SUM(разметка!F3:F151) -> 25 | C8: =IFERROR(B7/$B$3,0) -> 0 | D8: {=SUMPRODUCT(--(VALUE(разметка!C3:C153)<=3),разметка!F3:F153)} -> 24 | E8: =IFERROR(D7/$B$4,0) -> 0
A9: музыка_звук | B9: =SUM(разметка!H3:H151) -> 4 | C9: =IFERROR(B9/$B$3,0) -> 0.026845638 | D9: =SUMPRODUCT(--(VALUE(разметка!C3:C151)<=3),разметка!H3:H151) -> 4 | E9: =IFERROR(D9/$B$4,0) -> 0.074074074
A10: персонал_сервис | B10: =SUM(разметка!I3:I151) -> 18 | C10: =IFERROR(B10/$B$3,0) -> 0.12080537 | D10: =SUMPRODUCT(--(VALUE(разметка!C3:C151)<=3),разметка!I3:I151) -> 16 | E10: =IFERROR(D10/$B$4,0) -> 0.2962963
A11: бар_еда | B11: =SUM(разметка!J3:J151) -> 8 | C11: =IFERROR(B11/$B$3,0) -> 0.053691275 | D11: =SUMPRODUCT(--(VALUE(разметка!C3:C151)<=3),разметка!J3:J151) -> 8 | E11: =IFERROR(D11/$B$4,0) -> 0.14814815
A12: помещение_комфорт | B12: =SUM(разметка!K3:K151) -> 12 | C12: =IFERROR(B12/$B$3,0) -> 0.080536913 | D12: =SUMPRODUCT(--(VALUE(разметка!C3:C151)<=3),разметка!K3:K151) -> 10 | E12: =IFERROR(D12/$B$4,0) -> 0.18518519
A13: цены_финвопросы | B13: =SUM(разметка!L3:L151) -> 15 | C13: =IFERROR(B13/$B$3,0) -> 0.10067114 | D13: =SUMPRODUCT(--(VALUE(разметка!C3:C151)<=3),разметка!L3:L151) -> 13 | E13: =IFERROR(D13/$B$4,0) -> 0.24074074
A14: платный_вход | B14: =SUM(разметка!M3:M151) -> 5 | C14: =IFERROR(B14/$B$3,0) -> 0.033557047 | D14: =SUMPRODUCT(--(VALUE(разметка!C3:C151)<=3),разметка!M3:M151) -> 4 | E14: =IFERROR(D14/$B$4,0) -> 0.074074074
A15: безопасность_кражи | B15: =SUM(разметка!N3:N151) -> 1 | C15: =IFERROR(B15/$B$3,0) -> 0.0067114094 | D15: =SUMPRODUCT(--(VALUE(разметка!C3:C151)<=3),разметка!N3:N151) -> 1 | E15: =IFERROR(D15/$B$4,0) -> 0.018518519
A16: контингент | B16: =SUM(разметка!P3:P151) -> 4 | C16: =IFERROR(B16/$B$3,0) -> 0.026845638 | D16: =SUMPRODUCT(--(VALUE(разметка!C3:C151)<=3),разметка!P3:P151) -> 4 | E16: =IFERROR(D16/$B$4,0) -> 0.074074074
A17: прочее | B17: =SUM(разметка!O3:O151) -> 7 | C17: =IFERROR(B17/$B$3,0) -> 0.046979866 | D17: =SUMPRODUCT(--(VALUE(разметка!C3:C151)<=3),разметка!O3:O151) -> 5 | E17: =IFERROR(D17/$B$4,0) -> 0.092592593
A19: Отзывов без единой темы | B19: {=SUMPRODUCT(--((разметка!F3:F151+разметка!G3:G151+разметка!H3:H151+разметка!I3:I151+разметка!J3:J151+разметка!K3:K151+разметка!L3:L151+разметка!M3:M151+разметка!N3:N151+разметка!P3:P151+разметка!O3:O151)=0))} -> 91
A20: Тем на отзыв в среднем | B20: =IFERROR(SUM(B7:B17)/B3,0) -> 0.66442953
